README.rst
setup.py
src/projection/__init__.py
src/projection.egg-info/PKG-INFO
src/projection.egg-info/SOURCES.txt
src/projection.egg-info/dependency_links.txt
src/projection.egg-info/entry_points.txt
src/projection.egg-info/requires.txt
src/projection.egg-info/top_level.txt